sbq/__init__.py
sbq/sbq.py
sbq-0.1.0.dist-info/DESCRIPTION.rst
sbq-0.1.0.dist-info/METADATA
sbq-0.1.0.dist-info/metadata.json
sbq-0.1.0.dist-info/RECORD
sbq-0.1.0.dist-info/top_level.txt
sbq-0.1.0.dist-info/WHEEL
