Metadata-Version: 2.0
Name: sbq
Version: 0.1.0
Summary: Low-dependency package for automating bigquery queries.
Home-page: github.com/cjfuller/sbq
Author: Colin Fuller
Author-email: colin@khanacademy.org
License: UNKNOWN
Keywords: bigquery
Platform: UNKNOWN
Classifier: Programming Language :: Python
Classifier: License :: OSI Approved :: MIT
Classifier: Operating System :: OS Independent
Requires: requests
